biomero/__init__.py
biomero/constants.py
biomero/database.py
biomero/eventsourcing.py
biomero/slurm_client.py
biomero/views.py
docs/Makefile
docs/biomero.rst
docs/conf.py
docs/index.rst
docs/make.bat
docs/modules.rst
docs/readme_link.md
docs/requirements.txt
docs/slurm-configuration.rst
docs/tutorial_link.md
docs/developer/eventsourcing.rst
resources/__init__.py
resources/convert_job_array.sh
resources/convert_zarr_to_tiff.def
resources/convert_zarr_to_tiff.dockerfile
resources/convert_zarr_to_tiff.py
resources/example.config
resources/job_template.sh
resources/pull_images.sh
resources/slurm-config.ini
resources/tutorials/tutorial_Azure_slurm.md
resources/tutorials/tutorial_GoogleCloud_slurm.md
resources/tutorials/tutorial_cellexpansion.md
resources/tutorials/tutorial_cellprofiler.md
resources/tutorials/tutorial_local_slurm.md
resources/tutorials/images/Cells.tif
resources/tutorials/images/cellexpansion.png
resources/tutorials/images/gc_allow_ssh.PNG
resources/tutorials/images/nuclei_labels.png
resources/tutorials/images/webclient_init_env.PNG
resources/tutorials/images/webclient_init_env_done.PNG
resources/tutorials/images/webclient_run_cellpose.PNG
resources/tutorials/images/webclient_run_workflow.PNG
tests/integration/__init__.py
tests/unit/__init__.py
tests/unit/test_eventsourcing.py
tests/unit/test_slurm_client.py
biomero-2.1.0.dist-info/LICENSE
biomero-2.1.0.dist-info/METADATA
biomero-2.1.0.dist-info/WHEEL
biomero-2.1.0.dist-info/top_level.txt
biomero-2.1.0.dist-info/RECORD
