Metadata-Version: 2.1
Name: biomero
Version: 2.1.0
Summary: A python library for easy connecting between OMERO (jobs) and a Slurm cluster
Author: Core Facility - Cellular Imaging
Author-email: Torec Luik <t.t.luik@amsterdamumc.nl>, cellularimaging@amsterdamumc.nl
License: Apache License
Project-URL: Homepage, https://github.com/NL-BioImaging/biomero
Project-URL: Documentation, https://nl-bioimaging.github.io/biomero/
Keywords: omero,slurm,high-performance-computing,fair,image-analysis,bioimaging,high-throughput-screening,high-content-screening,cytomine,biomero,biaflows
Classifier: Programming Language :: Python :: 3
Classifier: Programming Language :: Python :: 3.10
Classifier: Programming Language :: Python :: 3.11
Classifier: Programming Language :: Python :: 3.12
Classifier: License :: OSI Approved :: Apache Software License
Classifier: Operating System :: OS Independent
Requires-Python: >=3.10
License-File: LICENSE
Requires-Dist: requests ==2.32.4
Requires-Dist: requests-cache ==1.1.1
Requires-Dist: fabric ==3.1.0
Requires-Dist: paramiko ==3.4.0
Requires-Dist: importlib-resources >=5.4.0
Requires-Dist: eventsourcing ==9.3
Requires-Dist: sqlalchemy ==2.0.32
Requires-Dist: psycopg2 ==2.9.9
Requires-Dist: eventsourcing-sqlalchemy ==0.9
Provides-Extra: full
Requires-Dist: ezomero >=1.1.1 ; extra == 'full'
Requires-Dist: tifffile >=2020.9.3 ; extra == 'full'
Requires-Dist: omero-metadata >=0.12.0 ; extra == 'full'
Requires-Dist: omero-cli-zarr >=0.6.1 ; extra == 'full'
Provides-Extra: test
Requires-Dist: pytest ; extra == 'test'
Requires-Dist: pytest-cov ; extra == 'test'
Requires-Dist: mock ; extra == 'test'
Requires-Dist: flake8 ; extra == 'test'
Requires-Dist: psycopg2-binary ; extra == 'test'
